LICENSE
README.md
setup.cfg
setup.py
./scripts/liquilt
liquilt/cli.py
liquilt.egg-info/PKG-INFO
liquilt.egg-info/SOURCES.txt
liquilt.egg-info/dependency_links.txt
liquilt.egg-info/requires.txt
liquilt.egg-info/top_level.txt