Metadata-Version: 1.2
Name: liquilt
Version: 0.2
Summary: Create 3D views of a quilt!
Home-page: UNKNOWN
Author: Peter Willemsen <peter@codebuffet.co>
License: UNKNOWN
Platform: UNKNOWN
Requires-Python: >=3.5
